sop_utils/__init__.py
sop_utils/models.py
sop_utils/utils.py
sop_utils/static/my_quicksearch.js
sop_utils/static/my_tab.js
sop_utils/templates/sop_utils/tools/badge.html
sop_utils/templates/sop_utils/tools/breadcrumbs.html
sop_utils/templates/sop_utils/tools/display.html
sop_utils/templates/sop_utils/tools/form.html
sop_utils/templates/sop_utils/tools/site.html
sop_utils/templates/sop_utils/tools/table.html
sop_utils-1.0.7.dist-info/METADATA
sop_utils-1.0.7.dist-info/WHEEL
sop_utils-1.0.7.dist-info/top_level.txt
sop_utils-1.0.7.dist-info/RECORD
